{
  "name": "@ot-builder/cli-help-shower",
  "entries": [
    {
      "date": "Mon, 23 Nov 2020 01:14:22 GMT",
      "tag": "@ot-builder/cli-help-shower_v0.10.34",
      "version": "0.10.34",
      "comments": {
        "patch": [
          {
            "comment": "OT184 IVD change",
            "author": "c@cyano.cn",
            "commit": "b1e4ea8a6fc06fa40af892956f275194b439fb9c",
            "package": "@ot-builder/cli-help-shower"
          }
        ]
      }
    },
    {
      "date": "Sun, 11 Oct 2020 00:13:03 GMT",
      "tag": "@ot-builder/cli-help-shower_v0.10.29",
      "version": "0.10.29",
      "comments": {
        "patch": [
          {
            "comment": "Add repository data to Packages' package.json",
            "author": "otbbuilder-dev@users.noreply.github.com",
            "commit": "cf9c159d8036dee65dd8819cc1e8df5feecd87bc",
            "package": "@ot-builder/cli-help-shower"
          }
        ]
      }
    },
    {
      "date": "Sun, 27 Sep 2020 00:12:54 GMT",
      "tag": "@ot-builder/cli-help-shower_v0.10.26",
      "version": "0.10.26",
      "comments": {
        "patch": [
          {
            "comment": "CLI: Export optimization options",
            "author": "belleve@typeof.net",
            "commit": "7dec567dd81f5b16f5ff514f55559e70dbebf6cb",
            "package": "@ot-builder/cli-help-shower"
          }
        ]
      }
    },
    {
      "date": "Fri, 25 Sep 2020 09:16:28 GMT",
      "tag": "@ot-builder/cli-help-shower_v0.10.25",
      "version": "0.10.25",
      "comments": {
        "patch": [
          {
            "comment": "Lift out CLI help shower to separate module; Add TTC input for TTC bundler",
            "author": "belleve@typeof.net",
            "commit": "18463c312a75db7285d0939b8f775edbf04eac90",
            "package": "@ot-builder/cli-help-shower"
          }
        ]
      }
    }
  ]
}
